_funcs.cpython-310-darwin.so
_geographic.cpython-310-darwin.so
gdp/__init__.py
gdp/_funcs.c
gdp/_funcs.pyx
gdp/_geographic.c
gdp/_geographic.pyx
gdp/conv.py
gdp/dat.py
gdp/funcs.py
gdp/geographic.py
gdp/io.py
gdp/main.py
gdp/nan.py
gdp-0.1.1.dist-info/LICENSE
gdp-0.1.1.dist-info/METADATA
gdp-0.1.1.dist-info/WHEEL
gdp-0.1.1.dist-info/entry_points.txt
gdp-0.1.1.dist-info/top_level.txt
gdp-0.1.1.dist-info/RECORD
