Metadata-Version: 2.1
Name: gdp
Version: 0.1.1
Summary: a set of tools for geophysical data processing
Home-page: https://github.com/omid-b/gdp
Author: omid-b
Author-email: omid.bagherpur@gmail.com
License: UNKNOWN
Platform: UNKNOWN
Classifier: Programming Language :: Python :: 3
Classifier: License :: OSI Approved :: GNU Lesser General Public License v3 or later (LGPLv3+)
Classifier: Operating System :: OS Independent
Requires-Python: >=3.6
License-File: LICENSE
Requires-Dist: numpy (>=1.19)
Requires-Dist: pandas (>=1.1)
Requires-Dist: obspy (>=1.2)
Requires-Dist: Cython (>=0.29.21)
Requires-Dist: geopandas
Requires-Dist: netCDF4
